<!--
DO NOT ALTER OR REMOVE COPYRIGHT NOTICES OR THIS HEADER.

Copyright 1997-2007 Sun Microsystems, Inc. All rights reserved.


The contents of this file are subject to the terms of either the GNU
General Public License Version 2 only ("GPL") or the Common
Development and Distribution License("CDDL") (collectively, the
"License"). You may not use this file except in compliance with the
License. You can obtain a copy of the License at
http://www.netbeans.org/cddl-gplv2.html
or nbbuild/licenses/CDDL-GPL-2-CP. See the License for the
specific language governing permissions and limitations under the
License.  When distributing the software, include this License Header
Notice in each file and include the License file at
nbbuild/licenses/CDDL-GPL-2-CP.  Sun designates this
particular file as subject to the "Classpath" exception as provided
by Sun in the GPL Version 2 section of the License file that
accompanied this code. If applicable, add the following below the
License Header, with the fields enclosed by brackets [] replaced by
your own identifying information:
"Portions Copyrighted [year] [name of copyright owner]"

Contributor(s):

The Original Software is the LaTeX module. The Initial Developer of the Original
Software is Jan Lahoda. Portions Copyright 2003-2006 Sun
Microsystems, Inc. All Rights Reserved.

If you wish your version of this file to be governed by only the CDDL
or only the GPL Version 2, indicate your decision by adding
"[Contributor] elects to include this software in this distribution
under the [CDDL or GPL Version 2] license." If you do not indicate a
single choice of license, a recipient has the option to distribute
your version of this file under either the CDDL, the GPL Version 2 or
to extend the choice of license to its licensees as provided above.
However, if you add GPL Version 2 code and therefore, elected the GPL
Version 2 license, then the option applies only if the new code is
made subject to such option by the copyright holder.
-->
<environment name="table">
    <attribute name="#table-environment" value="true" />
    <attribute name="#captionable" value="true" />
    <commands>
        <command name="\caption">
          <attribute name="#caption-command" value="true" />
          <argument type="mandatory">
            <attribute name="#text" value="true" />

            <attribute name="#caption" value="true" />
          </argument>
        </command>
    </commands>
</environment>

<environment name="itemize">
    <attribute name="hide-environment-boundary" value="true" />
    <attribute name="item-block" value="item-itemize" />
    <attribute name="par" value="true" />
    <commands>
        <command name="\item">
          <attribute name="par" value="true" />
          <attribute name="free-text-end" value="true" />
          <attribute name="hide-command" value="true" />
          <attribute name="item-command" value="true" />
          <attribute name="visual-caret-marker" value="true" />
          <argument type="nonmandatory">
            <attribute name="#code" value="true" />
            <attribute name="item-description-argument" value="true" />
            <attribute name="hide-surrounding-brackets" value="true" />
          </argument>

          <argument type="free">
            <attribute name="#text" value="true" />
            <attribute name="item-argument" value="item-itemize" />
            <attribute name="item-formating-level-1" value="- " />
            <attribute name="item-formating-level-2" value="- " />
            <attribute name="item-formating-level-3" value="- " />
            <attribute name="item-formating-level-4" value="- " />
            <attribute name="contains-paragraph" value="true" />
            <attribute name="hide-surrounding-brackets" value="true" />
          </argument>
        </command>
    </commands>
</environment>

<environment name="figure">
    <attribute name="#figure-environment" value="true" />
    <attribute name="#captionable" value="true" />
    <attribute name="figure-environment" value="true" />
    <attribute name="hide-environment-boundary" value="true" />
    <commands>
        <command name="\caption">
          <attribute name="#caption-command" value="true" />
          <argument type="mandatory">
            <attribute name="#text" value="true" />

            <attribute name="#caption" value="true" />
          </argument>
        </command>
    </commands>
</environment>

<environment name="abstract"></environment>

<environment name="description">
    <attribute name="hide-environment-boundary" value="true" />
    <attribute name="item-block" value="item-description" />
    <attribute name="par" value="true" />
    <commands>
        <command name="\item">
          <attribute name="par" value="true" />
          <attribute name="free-text-end" value="true" />
          <attribute name="hide-command" value="true" />
          <attribute name="item-command" value="true" />
          <attribute name="visual-caret-marker" value="true" />
          <argument type="nonmandatory">
            <attribute name="#code" value="true" />
            <attribute name="item-description-argument" value="true" />
            <attribute name="font-style" value="bold" />
            <attribute name="hide-surrounding-brackets" value="true" />
          </argument>

          <argument type="free">
            <attribute name="#text" value="true" />
            <attribute name="item-argument" value="item-description" />
            <attribute name="item-formating-level-1" value="" />
            <attribute name="item-formating-level-2" value="" />
            <attribute name="item-formating-level-3" value="" />
            <attribute name="item-formating-level-4" value="" />
            <attribute name="contains-paragraph" value="true" />
            <attribute name="hide-surrounding-brackets" value="true" />
          </argument>
        </command>
    </commands>
</environment>

<environment name="document">
    <attribute name="hide-environment-boundary" value="true" />
</environment>

<environment name="center"></environment>

<environment name="flushleft"></environment>

<environment name="flushright"></environment>

<environment name="tabular">
    <commands>
        <command name="\hline">
        </command>
        <command name="\cline">
        </command>
    </commands>
</environment>

<environment name="enumerate">
    <attribute name="hide-environment-boundary" value="true" />
    <attribute name="item-block" value="item-enumerate" />
    <attribute name="par" value="true" />
    <commands>
        <command name="\item">
          <attribute name="par" value="true" />
          <attribute name="free-text-end" value="true" />
          <attribute name="hide-command" value="true" />
          <attribute name="item-command" value="true" />
          <attribute name="visual-caret-marker" value="true" />
          <argument type="nonmandatory">
            <attribute name="#code" value="true" />
            <attribute name="item-description-argument" value="true" />
            <attribute name="hide-surrounding-brackets" value="true" />
          </argument>

          <argument type="free">
            <attribute name="#text" value="true" />
            <attribute name="item-argument" value="item-enumerate" />
            <attribute name="item-formating-level-1" value="{item-counter-level-item-enumerate-1}. " />
            <attribute name="item-formating-level-2" value="{item-counter-level-item-enumerate-2}. " />
            <attribute name="item-formating-level-3" value="{item-counter-level-item-enumerate-3}. " />
            <attribute name="item-formating-level-4" value="{item-counter-level-item-enumerate-4}. " />
            <attribute name="contains-paragraph" value="true" />
            <attribute name="hide-surrounding-brackets" value="true" />
          </argument>
        </command>
    </commands>
</environment>

<environment name="minipage"></environment>

<environment name="equation"></environment>

<environment name="quote"></environment>

<environment name="quotation"></environment>

<environment name="verbatim">
    <argument type="special">
        <attribute name="type" value="verbatim-env" />
        <attribute name="end-tag" value="\end{verbatim}" />
    </argument>
</environment>

<environment name="algorithmic">
    <attribute name="par" value="true" />
    <commands>
        <command name="\REQUIRE">
            <attribute name="par" value="true" />
            <argument type="free">
                <attribute name="#text" value="true" />
            </argument>
        </command>
        <command name="\ENSURE">
            <attribute name="par" value="true" />
            <argument type="free">
                <attribute name="#text" value="true" />
            </argument>
        </command>
        <command name="\STATE">
            <attribute name="par" value="true" />
            <argument type="free">
                <attribute name="#text" value="true" />
            </argument>
        </command>
        <command name="\COMMENT">
            <attribute name="par" value="true" />
            <argument type="free">
                <attribute name="#text" value="true" />
            </argument>
        </command>
        <command name="\FOR">
            <attribute name="par" value="true" />
            <argument type="free">
                <attribute name="#text" value="true" />
            </argument>
        </command>
        <command name="\FORALL">
            <attribute name="par" value="true" />
            <argument type="free">
                <attribute name="#text" value="true" />
            </argument>
        </command>
        <command name="\ENDFOR">
            <attribute name="par" value="true" />
        </command>
        <command name="\IF">
            <attribute name="par" value="true" />
            <argument type="free">
                <attribute name="#text" value="true" />
            </argument>
        </command>
        <command name="\ENDIF">
            <attribute name="par" value="true" />
        </command>
        <command name="\WHILE">
            <attribute name="par" value="true" />
            <argument type="free">
                <attribute name="#text" value="true" />
            </argument>
        </command>
        <command name="\ENDWHILE">
            <attribute name="par" value="true" />
        </command>
    </commands>
</environment>
