<?xml version="1.0" encoding="UTF-8"?>
<system-requements version="1.0" product-name="" product-version="" >
	<distributions>
		<distribution name="SuSE.*Enterprise.*" version="9.*" />
		<distribution name="SUSE Linux Enterprise Server" version="10.*" />
                <distribution name="SUSE Linux Enterprise Server" version="11.*" />
                <distribution name="Red Hat Enterprise Linux.*" version="4.*" />
                <distribution name="Red Hat Enterprise Linux.*" version="5.*" />
                <distribution name="OpenSolaris" version=".*" />
                <distribution name="Solaris" version="9.*" />
                <distribution name="Solaris" version="10.*" />
	</distributions>
	<hardware>
		<cpus>
			<cpu model=".*" minimum-frequency="450" />
		</cpus>
		<memory minimum-size="512" />
	</hardware>
        <!--
        <patches> // Solaris only
            <distribution name="OpenSolaris" version=".*" >
                <patch id="11111-12" />
            </distribution>
        </patches>
        -->
</system-requements>
