<?xml version="1.0" encoding="UTF-8"?>
<!DOCTYPE filesystem PUBLIC "-//NetBeans//DTD Filesystem 1.1//EN" "http://www.netbeans.org/dtds/filesystem-1_1.dtd">
<filesystem>
    <folder name="Navigator">
        <folder name="Panels">
            <folder name="text">
                <folder name="x-java">
                    <file name="org-netbeans-modules-javanavigators-JavaMembersNavigator.instance">
                        <attr name="position" intvalue="50"/>
                    </file>
                </folder>
            </folder>
        </folder>
    </folder>
</filesystem>
