<?xml version="1.0" encoding="UTF-8"?>
<!--
DO NOT ALTER OR REMOVE COPYRIGHT NOTICES OR THIS HEADER.

Copyright 1997-2007 Sun Microsystems, Inc. All rights reserved.


The contents of this file are subject to the terms of either the GNU
General Public License Version 2 only ("GPL") or the Common
Development and Distribution License("CDDL") (collectively, the
"License"). You may not use this file except in compliance with the
License. You can obtain a copy of the License at
http://www.netbeans.org/cddl-gplv2.html
or nbbuild/licenses/CDDL-GPL-2-CP. See the License for the
specific language governing permissions and limitations under the
License.  When distributing the software, include this License Header
Notice in each file and include the License file at
nbbuild/licenses/CDDL-GPL-2-CP.  Sun designates this
particular file as subject to the "Classpath" exception as provided
by Sun in the GPL Version 2 section of the License file that
accompanied this code. If applicable, add the following below the
License Header, with the fields enclosed by brackets [] replaced by
your own identifying information:
"Portions Copyrighted [year] [name of copyright owner]"

Contributor(s):

The Original Software is NetBeans. The Initial Developer of the Original
Software is Sun Microsystems, Inc. Portions Copyright 1997-2006 Sun
Microsystems, Inc. All Rights Reserved.

If you wish your version of this file to be governed by only the CDDL
or only the GPL Version 2, indicate your decision by adding
"[Contributor] elects to include this software in this distribution
under the [CDDL or GPL Version 2] license." If you do not indicate a
single choice of license, a recipient has the option to distribute
your version of this file under either the CDDL, the GPL Version 2 or
to extend the choice of license to its licensees as provided above.
However, if you add GPL Version 2 code and therefore, elected the GPL
Version 2 license, then the option applies only if the new code is
made subject to such option by the copyright holder.
-->

<!--
@author Caoyuan Deng
-->

<documentation>
    <node key="include()."     context="attribute" type="constructor" library="Predefined Attribute"/>
    <node key="include_lib()." context="attribute" type="constructor" library="Predefined Attribute"/>
    <node key="define()"       context="attribute" type="constructor" library="Predefined Attribute"/>
    <node key="undef."         context="attribute" type="constructor" library="Predefined Attribute"/>
    <node key="ifdef()."       context="attribute" type="constructor" library="Predefined Attribute"/>
    <node key="ifndef()."      context="attribute" type="constructor" library="Predefined Attribute"/>
    <node key="else."          context="attribute" type="constructor" library="Predefined Attribute"/>
    <node key="endif."         context="attribute" type="constructor" library="Predefined Attribute"/>
    <node key="compile()."     context="attribute" type="constructor" library="Predefined Attribute"/>
    <node key="module()."      context="attribute" type="constructor" library="Predefined Attribute"/>
    <node key="import()."      context="attribute" type="constructor" library="Predefined Attribute"/>
    <node key="export([])."    context="attribute" type="constructor" library="Predefined Attribute"/>
    <node key="behaviour()."   context="attribute" type="constructor" library="Predefined Attribute"/>
    <node key="author()."      context="attribute" type="constructor" library="Predefined Attribute"/>
    <node key="vsn()."         context="attribute" type="constructor" library="Predefined Attribute"/>
    <node key="doc()."         context="attribute" type="constructor" library="Predefined Attribute"/>
    <node key="copyright()."   context="attribute" type="constructor" library="Predefined Attribute"/>
    <node key="file()."        context="attribute" type="constructor" library="Predefined Attribute"/>

    <node key="after"          context="keyword" type="keyword" library="Erlang keyword"/>
    <node key="begin"          context="keyword" type="keyword" library="Erlang keyword"/>
    <node key="case"           context="keyword" type="keyword" library="Erlang keyword"/>
    <node key="try"            context="keyword" type="keyword" library="Erlang keyword"/>
    <node key="catch"          context="keyword" type="keyword" library="Erlang keyword"/>
    <node key="end"            context="keyword" type="keyword" library="Erlang keyword"/>
    <node key="fun"            context="keyword" type="keyword" library="Erlang keyword"/>
    <node key="if"             context="keyword" type="keyword" library="Erlang keyword"/>
    <node key="of"             context="keyword" type="keyword" library="Erlang keyword"/>
    <node key="receive"        context="keyword" type="keyword" library="Erlang keyword"/>
    <node key="when"           context="keyword" type="keyword" library="Erlang keyword"/>
    <node key="andalso"        context="keyword" type="keyword" library="Erlang keyword"/>
    <node key="orelse"         context="keyword" type="keyword" library="Erlang keyword"/>
    <node key="query"          context="keyword" type="keyword" library="Erlang keyword"/>
    <node key="cond"           context="keyword" type="keyword" library="Erlang keyword"/>
    <node key="div"            context="keyword" type="keyword" library="Integer division"/>
    <node key="rem"            context="keyword" type="keyword" library="Integer remainder of X/Y"/>
    <node key="bnot"           context="keyword" type="keyword" library="Unary bitwise not"/>
    <node key="band"           context="keyword" type="keyword" library="Bitwise and"/>
    <node key="bor"            context="keyword" type="keyword" library="Bitwise or"/>
    <node key="bxor"           context="keyword" type="keyword" library="Arithmetic bitwise xor"/>
    <node key="bsl"            context="keyword" type="keyword" library="Arithmetic bitshift left"/>
    <node key="bsr"            context="keyword" type="keyword" library="Arithmetic Bitshift right"/>
    <node key="not"            context="keyword" type="keyword" library="Unary logical not"/>
    <node key="and"            context="keyword" type="keyword" library="Logical and"/>
    <node key="or"             context="keyword" type="keyword" library="Logical or"/>
    <node key="xor"            context="keyword" type="keyword" library="Logical xor"/>
    
    <node key="abs(Number)"                                 context="builtin" type="method" library="Built-in Function"/>
    <node key="append_element({one, two}, three)"           context="erlang"  type="method" library="Built-in Function"/>
    <node key="apply(Fun, Args)"                            context="builtin" type="method" library="Built-in Function"/>
    <node key="apply(Module, Function, Args)"               context="builtin" type="method" library="Built-in Function"/>
    <node key="atom_to_list(Atom)"                          context="builtin" type="method" library="Built-in Function"/>
    <node key="binary_to_float(Binary)"                     context="builtin" type="method" library="Built-in Function"/>
    <node key="binary_to_list(Binary)"                      context="builtin" type="method" library="Built-in Function"/>
    <node key="binary_to_list(Binary, Start, Stop)"         context="builtin" type="method" library="Built-in Function"/>
    <node key="binary_to_term(Binary)"                      context="builtin" type="method" library="Built-in Function"/>
    <node key="bit_size(Binary)"                            context="builtin" type="method" library="Built-in Function"/>
    <node key="bump_reductions(Reductions)"                 context="erlang"  type="method" library="Built-in Function"/>
    <node key="byte_size(Binary)"                           context="builtin" type="method" library="Built-in Function"/>
    <node key="cancel_timer(TimerRef)"                      context="erlang"  type="method" library="Built-in Function"/>
    <node key="check_process_code(Pid, Module)"             context="builtin" type="method" library="Built-in Function"/>
    <node key="date()"                                      context="builtin" type="method" library="Built-in Function"/>
    <node key="delete_module(Module)"                       context="builtin" type="method" library="Built-in Function"/>
    <node key="demonitor(MonitorRef)"                       context="erlang"  type="method" library="Built-in Function"/>
    <node key="demonitor(MonitorRef, OptionList)"           context="erlang"  type="method" library="Built-in Function"/>
    <node key="disconnect_node(Node)"                       context="builtin" type="method" library="Built-in Function"/>
    <node key="display(Term)"                               context="erlang"  type="method" library="Built-in Function"/>
    <node key="element(N, Tuple)"                           context="builtin" type="method" library="Built-in Function"/>
    <node key="erase()"                                     context="builtin" type="method" library="Built-in Function"/>
    <node key="erase(Key)"                                  context="builtin" type="method" library="Built-in Function"/>
    <node key="error(Reason)"                               context="erlang"  type="method" library="Built-in Function"/>
    <node key="error(Reason, Args)"                         context="erlang"  type="method" library="Built-in Function"/>
    <node key="exit(Reason)"                                context="builtin" type="method" library="Built-in Function"/>
    <node key="exit(Pid, Reason)"                           context="builtin" type="method" library="Built-in Function"/>
    <node key="fault(Reason)"                               context="erlang"  type="method" library="Built-in Function"/>
    <node key="fault(Reason, Args)"                         context="erlang"  type="method" library="Built-in Function"/>
    <node key="float(Number)"                               context="builtin" type="method" library="Built-in Function"/>
    <node key="float_to_list(Float)"                        context="builtin" type="method" library="Built-in Function"/>
    <node key="float_to_binary"                             context="builtin" type="method" library="Built-in Function"/>
    <node key="fun_info(Fun)"                               context="erlang"  type="method" library="Built-in Function"/>
    <node key="fun_info(Fun, Item)"                         context="erlang"  type="method" library="Built-in Function"/>
    <node key="fun_to_list(Fun)"                            context="erlang"  type="method" library="Built-in Function"/>
    <node key="function_exported(Module, Function, Arity)"  context="erlang"  type="method" library="Built-in Function"/>
    <node key="garbage_collect()"                           context="builtin" type="method" library="Built-in Function"/>
    <node key="garbage_collect(Pid)"                        context="builtin" type="method" library="Built-in Function"/>
    <node key="get()"                                       context="builtin" type="method" library="Built-in Function"/>
    <node key="get(Key)"                                    context="builtin" type="method" library="Built-in Function"/>
    <node key="get_cookie()"                                context="erlang"  type="method" library="Built-in Function"/>
    <node key="get_keys(Val)"                               context="builtin" type="method" library="Built-in Function"/>
    <node key="get_stacktrace()"                            context="erlang"  type="method" library="Built-in Function"/>
    <node key="group_leader()"                              context="builtin" type="method" library="Built-in Function"/>
    <node key="group_leader(GroupLeader, Pid)"              context="builtin" type="method" library="Built-in Function"/>
    <node key="halt()"                                      context="builtin" type="method" library="Built-in Function"/>
    <node key="halt(Status)"                                context="builtin" type="method" library="Built-in Function"/>
    <node key="hash(Term, Range)"                           context="erlang"  type="method" library="Built-in Function"/>
    <node key="hd(List)"                                    context="builtin" type="method" library="Built-in Function"/>
    <node key="hibernate(Module, Function, Args)"           context="erlang"  type="method" library="Built-in Function"/>
    <node key="info(Type)"                                  context="erlang"  type="method" library="Built-in Function"/>
    <node key="integer_to_list(Integer)"                    context="builtin" type="method" library="Built-in Function"/>
    <node key="integer_to_list(Integer, Base)"              context="erlang"  type="method" library="Built-in Function"/>
    <node key="iolist_to_binary(IoListOrBinary)"            context="builtin" type="method" library="Built-in Function"/>
    <node key="iolist_size(Item)"                           context="builtin" type="method" library="Built-in Function"/>
    <node key="is_alive()"                                  context="builtin" type="method" library="Built-in Function"/>
    <node key="is_atom(Term)"                               context="builtin" type="method" library="Built-in Function"/>
    <node key="is_binary(Term)"                             context="builtin" type="method" library="Built-in Function"/>
    <node key="is_boolean(Term)"                            context="builtin" type="method" library="Built-in Function"/>
    <node key="is_builtin(Module, Function, Arity)"         context="erlang"  type="method" library="Built-in Function"/>
    <node key="is_constant"                                 context="builtin" type="method" library="Built-in Function"/>
    <node key="is_float(Term)"                              context="builtin" type="method" library="Built-in Function"/>
    <node key="is_function(Term)"                           context="builtin" type="method" library="Built-in Function"/>
    <node key="is_integer(Term)"                            context="builtin" type="method" library="Built-in Function"/>
    <node key="is_list(Term)"                               context="builtin" type="method" library="Built-in Function"/>
    <node key="is_number(Term)"                             context="builtin" type="method" library="Built-in Function"/>
    <node key="is_pid(Term)"                                context="builtin" type="method" library="Built-in Function"/>
    <node key="is_port(Term)"                               context="builtin" type="method" library="Built-in Function"/>
    <node key="is_process_alive(Pid)"                       context="builtin" type="method" library="Built-in Function"/>
    <node key="is_record(Term, RecordTag)"                  context="builtin" type="method" library="Built-in Function"/>
    <node key="is_record(Term, RecordTag, Size)"            context="builtin" type="method" library="Built-in Function"/>
    <node key="is_reference(Term)"                          context="builtin" type="method" library="Built-in Function"/>
    <node key="is_tuple(Term)"                              context="builtin" type="method" library="Built-in Function"/>
    <node key="length(List)"                                context="builtin" type="method" library="Built-in Function"/>
    <node key="link(Pid)"                                   context="builtin" type="method" library="Built-in Function"/>
    <node key="list_to_atom(String)"                        context="builtin" type="method" library="Built-in Function"/>
    <node key="list_to_binary(IoList)"                      context="builtin" type="method" library="Built-in Function"/>
    <node key="list_to_existing_atom(String)"               context="builtin" type="method" library="Built-in Function"/>
    <node key="list_to_float(String)"                       context="builtin" type="method" library="Built-in Function"/>
    <node key="list_to_integer(String)"                     context="builtin" type="method" library="Built-in Function"/>
    <node key="list_to_integer(String, Base)"               context="erlang"  type="method" library="Built-in Function"/>
    <node key="list_to_pid(String)"                         context="builtin" type="method" library="Built-in Function"/>
    <node key="list_to_tuple(List)"                         context="builtin" type="method" library="Built-in Function"/>
    <node key="load_module(Module, Binary)"                 context="builtin" type="method" library="Built-in Function"/>
    <node key="loaded()"                                    context="erlang"  type="method" library="Built-in Function"/>
    <node key="localtime()"                                 context="erlang"  type="method" library="Built-in Function"/>
    <node key="localtime_to_universaltime({Date1, Time1})"  context="erlang"  type="method" library="Built-in Function"/>
    <node key="localtime_to_universaltime({Date1, Time1}, isDst)"  context="erlang"  type="method" library="Built-in Function"/>
    <node key="make_ref()"                                  context="builtin" type="method" library="Built-in Function"/>
    <node key="make_tuple(Arity, InitialValue)"             context="erlang"  type="method" library="Built-in Function"/>
    <node key="md5(Data)"                                   context="erlang"  type="method" library="Built-in Function"/>
    <node key="md5_final(Context)"                          context="erlang"  type="method" library="Built-in Function"/>
    <node key="md5_init()"                                  context="erlang"  type="method" library="Built-in Function"/>
    <node key="md5_update(Context, Data)"                   context="erlang"  type="method" library="Built-in Function"/>
    <node key="memory()"                                    context="erlang"  type="method" library="Built-in Function"/>
    <node key="memory(Type)"                                context="erlang"  type="method" library="Built-in Function"/>
    <node key="memory([Type])"                              context="erlang"  type="method" library="Built-in Function"/>
    <node key="module_loaded(Module)"                       context="builtin" type="method" library="Built-in Function"/>
    <node key="monitor(Type, Item)"                         context="erlang"  type="method" library="Built-in Function"/>
    <node key="monitor_node(Node, Flag)"                    context="builtin" type="method" library="Built-in Function"/>
    <node key="monitor_node(Node, Flag, Options)"           context="erlang"  type="method" library="Built-in Function"/>
    <node key="ncat_binary"                                 context="builtin" type="method" library="Built-in Function"/>
    <node key="node()"                                      context="builtin" type="method" library="Built-in Function"/>
    <node key="nodes()"                                     context="builtin" type="method" library="Built-in Function"/>
    <node key="nodes(Arg)"                                  context="builtin" type="method" library="Built-in Function"/>
    <node key="nodes([Arg])"                                context="builtin" type="method" library="Built-in Function"/>
    <node key="now()"                                       context="builtin" type="method" library="Built-in Function"/>
    <node key="open_port(PortName, PortSettings)"           context="builtin" type="method" library="Built-in Function"/>
    <node key="phash(Term, Range)"                          context="erlang"  type="method" library="Built-in Function"/>
    <node key="phash2(Term)"                                context="erlang"  type="method" library="Built-in Function"/>
    <node key="phash2(Term, Range)"                         context="erlang"  type="method" library="Built-in Function"/>
    <node key="pid_to_list(Pid)"                            context="builtin" type="method" library="Built-in Function"/>
    <node key="port_close(Port)"                            context="builtin" type="method" library="Built-in Function"/>
    <node key="port_command(Port, Data)"                    context="builtin" type="method" library="Built-in Function"/>
    <node key="port_connect(Port, Pid)"                     context="builtin" type="method" library="Built-in Function"/>
    <node key="port_control(Port, Operation, Data)"         context="builtin" type="method" library="Built-in Function"/>
    <node key="port_call(Port, Operation, Data)"            context="erlang"  type="method" library="Built-in Function"/>
    <node key="port_info(Port)"                             context="erlang"  type="method" library="Built-in Function"/>
    <node key="port_info(Port, Item)"                       context="erlang"  type="method" library="Built-in Function"/>
    <node key="port_to_list(Port)"                          context="erlang"  type="method" library="Built-in Function"/>
    <node key="ports()"                                     context="erlang"  type="method" library="Built-in Function"/>
    <node key="pre_loaded()"                                context="builtin" type="method" library="Built-in Function"/>
    <node key="process_display(Pid, Type)"                  context="erlang"  type="method" library="Built-in Function"/>
    <node key="process_flag(Flag, Value)"                   context="builtin" type="method" library="Built-in Function"/>
    <node key="process_flag(Pid, Flag, Value)"              context="builtin" type="method" library="Built-in Function"/>
    <node key="process_info(Pid)"                           context="builtin" type="method" library="Built-in Function"/>
    <node key="process_info(Pid, Item)"                     context="builtin" type="method" library="Built-in Function"/>
    <node key="processes()"                                 context="builtin" type="method" library="Built-in Function"/>
    <node key="purge_module(Module)"                        context="builtin" type="method" library="Built-in Function"/>
    <node key="put(Key, Val)"                               context="builtin" type="method" library="Built-in Function"/>
    <node key="raise(Class, Reason, Stacktrace)"            context="erlang"  type="method" library="Built-in Function"/>
    <node key="read_timer(TimerRef)"                        context="erlang"  type="method" library="Built-in Function"/>
    <node key="ref_to_list(Ref)"                            context="erlang"  type="method" library="Built-in Function"/>
    <node key="register(RegName, Pid)"                      context="builtin" type="method" library="Built-in Function"/>
    <node key="register(RegName, Port)"                     context="builtin" type="method" library="Built-in Function"/>
    <node key="registered()"                                context="builtin" type="method" library="Built-in Function"/>
    <node key="resume_process(Pid)"                         context="erlang"  type="method" library="Built-in Function"/>
    <node key="round(Number)"                               context="builtin" type="method" library="Built-in Function"/>
    <node key="self()"                                      context="builtin" type="method" library="Built-in Function"/>
    <node key="send(Dest, Msg)"                             context="erlang"  type="method" library="Built-in Function"/>
    <node key="send(Dest, Msg, [Option])"                   context="erlang"  type="method" library="Built-in Function"/>
    <node key="send_after(Time, Dest, Msg)"                 context="erlang"  type="method" library="Built-in Function"/>
    <node key="send_nosuspend(Dest, Msg)"                   context="erlang"  type="method" library="Built-in Function"/>
    <node key="send_nosuspend(Dest, Msg, Options)"          context="erlang"  type="method" library="Built-in Function"/>
    <node key="set_cookie(Node, Cookie)"                    context="erlang"  type="method" library="Built-in Function"/>
    <node key="setelement(Index, Tuple1, Value)"            context="builtin" type="method" library="Built-in Function"/>
    <node key="size(Item)"                                  context="builtin" type="method" library="Built-in Function"/>
    <node key="spawn(Fun)"                                  context="builtin" type="method" library="Built-in Function"/>
    <node key="spawn(Node, Fun)"                            context="builtin" type="method" library="Built-in Function"/>
    <node key="spawn(Module, Fun, Args)"                    context="builtin" type="method" library="Built-in Function"/>
    <node key="spawn(Node, Module, Fun, Args)"              context="builtin" type="method" library="Built-in Function"/>
    <node key="spawn_link(Fun)"                             context="builtin" type="method" library="Built-in Function"/>
    <node key="spawn_link(Node, Fun)"                       context="builtin" type="method" library="Built-in Function"/>
    <node key="spawn_link(Module, Fun, Args)"               context="builtin" type="method" library="Built-in Function"/>
    <node key="spawn_link(Node, Module, Fun, Args)"         context="builtin" type="method" library="Built-in Function"/>
    <node key="spawn_monitor(Fun)"                          context="erlang"  type="method" library="Built-in Function"/>
    <node key="spawn_monitor(Module, Function, Args)"       context="erlang"  type="method" library="Built-in Function"/>
    <node key="spawn_opt(Fun, [Option])"                    context="builtin" type="method" library="Built-in Function"/>
    <node key="spawn_opt(Node, Fun, [Option])"              context="builtin" type="method" library="Built-in Function"/>
    <node key="spawn_opt(Module, Node, Fun, [Option])"      context="builtin" type="method" library="Built-in Function"/>
    <node key="split_binary(Bin, Pos)"                      context="builtin" type="method" library="Built-in Function"/>
    <node key="start_timer(Time, Dest, Msg)"                context="erlang"  type="method" library="Built-in Function"/>
    <node key="statistics(Type)"                            context="builtin" type="method" library="Built-in Function"/>
    <node key="suspend_process(Pid)"                        context="erlang"  type="method" library="Built-in Function"/>
    <node key="system_flag(Flag, Value)"                    context="erlang"  type="method" library="Built-in Function"/>
    <node key="system_info(Type)"                           context="erlang"  type="method" library="Built-in Function"/>
    <node key="system_monitor()"                            context="erlang"  type="method" library="Built-in Function"/>
    <node key="system_monitor(undefined)"                   context="erlang"  type="method" library="Built-in Function"/>
    <node key="system_monitor({MonitorPid, Options})"       context="erlang"  type="method" library="Built-in Function"/>
    <node key="system_monitor(MonitorPid, [Option])"        context="erlang"  type="method" library="Built-in Function"/>
    <node key="term_to_binary(Term)"                        context="builtin" type="method" library="Built-in Function"/>
    <node key="term_to_binary(Term, [Option])"              context="builtin" type="method" library="Built-in Function"/>
    <node key="throw(Any)"                                  context="builtin" type="method" library="Built-in Function"/>
    <node key="time()"                                      context="builtin" type="method" library="Built-in Function"/>
    <node key="tl(List1)"                                   context="builtin" type="method" library="Built-in Function"/>
    <node key="trace(PidSpec, How, FlagList)"               context="erlang"  type="method" library="Built-in Function"/>
    <node key="trace_delivered(Tracee) "                    context="erlang"  type="method" library="Built-in Function"/>
    <node key="trace_info(PidOrFunc, Item)"                 context="erlang"  type="method" library="Built-in Function"/>
    <node key="trace_pattern(MFA, MatchSpec)"               context="erlang"  type="method" library="Built-in Function"/>
    <node key="trace_pattern(MFA, MatchSpec, FlagList)"     context="erlang"  type="method" library="Built-in Function"/>
    <node key="trunc(Number)"                               context="builtin" type="method" library="Built-in Function"/>
    <node key="tuple_size(Tuple)"                           context="builtin" type="method" library="Built-in Function"/>
    <node key="tuple_to_list(Tuple)"                        context="erlang"  type="method" library="Built-in Function"/>
    <node key="universaltime()"                             context="erlang"  type="method" library="Built-in Function"/>
    <node key="universaltime_to_localtime({Date1, Time1})"  context="builtin" type="method" library="Built-in Function"/>
    <node key="unlink(Id)"                                  context="builtin" type="method" library="Built-in Function"/>
    <node key="unregister(RegName)"                         context="builtin" type="method" library="Built-in Function"/>
    <node key="whereis(RegName)"                            context="builtin" type="method" library="Built-in Function"/>
    <node key="yield()"                                     context="erlang"  type="method" library="Built-in Function"/>

    
</documentation>
